MANIFEST.in
README.md
setup.py
kfinny/__init__.py
kfinny.starlette.egg-info/PKG-INFO
kfinny.starlette.egg-info/SOURCES.txt
kfinny.starlette.egg-info/dependency_links.txt
kfinny.starlette.egg-info/entry_points.txt
kfinny.starlette.egg-info/not-zip-safe
kfinny.starlette.egg-info/requires.txt
kfinny.starlette.egg-info/top_level.txt
kfinny/starlette/__init__.py
kfinny/starlette/app.py
kfinny/starlette/docs/404.png
kfinny/starlette/docs/500.png
kfinny/starlette/docs/index.png
kfinny/starlette/statics/css/bootstrap.min.css
kfinny/starlette/statics/css/jumbotron.css
kfinny/starlette/statics/js/bootstrap.min.js
kfinny/starlette/statics/js/jquery-3.3.1.slim.min.js
kfinny/starlette/statics/js/popper.min.js
kfinny/starlette/templates/404.html
kfinny/starlette/templates/500.html
kfinny/starlette/templates/base.html
kfinny/starlette/templates/index.html