Metadata-Version: 2.1
Name: kfinny.starlette
Version: 1.1
Summary: A pip-installable of starlette-example
Home-page: https://github.com/kfinny/starlette-pip-example
Author: Kevin Finnigin
Author-email: kevin@finnigin.net
License: MIT
Platform: UNKNOWN
